LICENSE
README.md
setup.py
oba/__init__.py
oba/oba.py
oba/path.py
oba/soba.py
oba.egg-info/PKG-INFO
oba.egg-info/SOURCES.txt
oba.egg-info/dependency_links.txt
oba.egg-info/requires.txt
oba.egg-info/top_level.txt