Metadata-Version: 2.4
Name: oba
Version: 0.3.1
Summary: make iter object easy to access (item to attr)
Home-page: https://github.com/Jyonn/Oba
Author: Jyonn Liu
Author-email: i@6-79.cn
License: MIT Licence
Keywords: dict,object
Platform: any
License-File: LICENSE
Requires-Dist: nestify
Dynamic: author
Dynamic: author-email
Dynamic: description
Dynamic: description-content-type
Dynamic: home-page
Dynamic: keywords
Dynamic: license
Dynamic: license-file
Dynamic: platform
Dynamic: requires-dist
Dynamic: summary
